pyproject2ebuild/__init__.py
pyproject2ebuild/main.py
pyproject2ebuild-0.0.4.dist-info/licenses/LICENSE.txt
pyproject2ebuild-0.0.4.dist-info/METADATA
pyproject2ebuild-0.0.4.dist-info/WHEEL
pyproject2ebuild-0.0.4.dist-info/entry_points.txt
pyproject2ebuild-0.0.4.dist-info/top_level.txt
pyproject2ebuild-0.0.4.dist-info/RECORD
