Metadata-Version: 2.4
Name: pyproject2ebuild
Version: 0.0.4
Summary: Convert pyproject.toml to Gentoo ebuilds automatically.
Author-email: Oz Tiram <oz.tiram@gmail.com>
License-Expression: GPL-3.0-or-later
Project-URL: Homepage, https://gitlab.com/oz123/pyproject2ebuild
Project-URL: Repository, https://gitlab/oz123/pyproject2ebuild
Project-URL: Issues, https://gitlab.com/oz123/pyproject2ebuild/-/issues
Requires-Python: >=3.9
License-File: LICENSE.txt
Requires-Dist: tomli; python_version < "3.11"
Provides-Extra: test
Requires-Dist: pytest; extra == "test"
Dynamic: license-file
